pcommand/__init__.py
pcommand/argument_parser.py
pcommand/command.py
pcommand/help_action.py
pcommand/help_formatter.py
pcommand/sub_parser_action.py
pcommand/utils.py
pcommand-0.2.1.dist-info/LICENSE
pcommand-0.2.1.dist-info/METADATA
pcommand-0.2.1.dist-info/WHEEL
pcommand-0.2.1.dist-info/top_level.txt
pcommand-0.2.1.dist-info/RECORD
