Metadata-Version: 2.1
Name: pcommand
Version: 0.2.1
Summary: attr: pcommand.__description__
Home-page: https://github.com/heitorpolidoro/polidoro-command
Author: attr: pcommand.__author__
License: MIT
Keywords: cli,command
Classifier: Programming Language :: Python :: 3
Requires-Python: >=3.9
License-File: LICENSE
